cloud_io/__init__.py
cloud_io/gcp/__init__.py
cloud_io/gcp/base.py
cloud_io/gcp/filesystem.py
cloud_io/gcp/io.py
cloud_io/tools/__init__.py
cloud_io/tools/common_path.py
cloud_io/tools/error.py
cloud_io-1.0.1.dist-info/LICENSE
cloud_io-1.0.1.dist-info/METADATA
cloud_io-1.0.1.dist-info/WHEEL
cloud_io-1.0.1.dist-info/top_level.txt
cloud_io-1.0.1.dist-info/RECORD
