Metadata-Version: 2.1
Name: cloud-io
Version: 1.0.1
Summary: Handle I/O from cloud buckets
Home-page: https://github.com/akouete-kpakpo/cloud_io
Author: (c) Akouete Kpakpo
Author-email: adkevinkpakpo@gmail.com
License: MIT
Platform: UNKNOWN
Classifier: Programming Language :: Python :: 3.8
Classifier: Operating System :: POSIX :: Linux
License-File: LICENSE
Requires-Dist: argon2-cffi (==21.3.0)
Requires-Dist: argon2-cffi-bindings (==21.2.0)
Requires-Dist: asttokens (==2.0.5)
Requires-Dist: attrs (==22.1.0)
Requires-Dist: backcall (==0.2.0)
Requires-Dist: beautifulsoup4 (==4.11.1)
Requires-Dist: black (==22.6.0)
Requires-Dist: bleach (==5.0.1)
Requires-Dist: cachetools (==5.2.0)
Requires-Dist: certifi (==2022.6.15)
Requires-Dist: cffi (==1.15.1)
Requires-Dist: charset-normalizer (==2.1.1)
Requires-Dist: click (==8.1.3)
Requires-Dist: debugpy (==1.6.2)
Requires-Dist: decorator (==5.1.1)
Requires-Dist: defusedxml (==0.7.1)
Requires-Dist: entrypoints (==0.4)
Requires-Dist: executing (==0.9.1)
Requires-Dist: fastjsonschema (==2.16.1)
Requires-Dist: flake8 (==5.0.3)
Requires-Dist: google-api-core (==2.8.2)
Requires-Dist: google-auth (==2.11.0)
Requires-Dist: google-cloud (==0.34.0)
Requires-Dist: google-cloud-core (==2.3.2)
Requires-Dist: google-cloud-storage (==2.5.0)
Requires-Dist: google-crc32c (==1.3.0)
Requires-Dist: google-resumable-media (==2.3.3)
Requires-Dist: googleapis-common-protos (==1.56.4)
Requires-Dist: idna (==3.3)
Requires-Dist: iniconfig (==1.1.1)
Requires-Dist: ipykernel (==6.15.1)
Requires-Dist: ipython (==8.4.0)
Requires-Dist: ipython-genutils (==0.2.0)
Requires-Dist: ipywidgets (==7.7.1)
Requires-Dist: jedi (==0.18.1)
Requires-Dist: jinja2 (==3.1.2)
Requires-Dist: jsonschema (==4.9.0)
Requires-Dist: jupyter (==1.0.0)
Requires-Dist: jupyter-client (==7.3.4)
Requires-Dist: jupyter-console (==6.4.4)
Requires-Dist: jupyter-core (==4.11.1)
Requires-Dist: jupyterlab-pygments (==0.2.2)
Requires-Dist: jupyterlab-widgets (==1.1.1)
Requires-Dist: markupsafe (==2.1.1)
Requires-Dist: matplotlib-inline (==0.1.3)
Requires-Dist: mccabe (==0.7.0)
Requires-Dist: mistune (==0.8.4)
Requires-Dist: mypy-extensions (==0.4.3)
Requires-Dist: nbclient (==0.6.6)
Requires-Dist: nbconvert (==6.5.0)
Requires-Dist: nbformat (==5.4.0)
Requires-Dist: nest-asyncio (==1.5.5)
Requires-Dist: notebook (==6.4.12)
Requires-Dist: numpy (==1.19.5)
Requires-Dist: packaging (==21.3)
Requires-Dist: pandas (==1.4.3)
Requires-Dist: pandocfilters (==1.5.0)
Requires-Dist: parso (==0.8.3)
Requires-Dist: pathspec (==0.9.0)
Requires-Dist: pep517 (==0.13.0)
Requires-Dist: pexpect (==4.8.0)
Requires-Dist: pickleshare (==0.7.5)
Requires-Dist: pip-tools (==6.6.0)
Requires-Dist: platformdirs (==2.5.2)
Requires-Dist: pluggy (==0.13.1)
Requires-Dist: prometheus-client (==0.14.1)
Requires-Dist: prompt-toolkit (==3.0.30)
Requires-Dist: protobuf (==4.21.5)
Requires-Dist: psutil (==5.9.1)
Requires-Dist: ptyprocess (==0.7.0)
Requires-Dist: pure-eval (==0.2.2)
Requires-Dist: py (==1.11.0)
Requires-Dist: pyasn1 (==0.4.8)
Requires-Dist: pyasn1-modules (==0.2.8)
Requires-Dist: pycodestyle (==2.9.0)
Requires-Dist: pycparser (==2.21)
Requires-Dist: pyflakes (==2.5.0)
Requires-Dist: pygments (==2.12.0)
Requires-Dist: pyparsing (==3.0.9)
Requires-Dist: pyrsistent (==0.18.1)
Requires-Dist: pytest (==6.2.4)
Requires-Dist: python-dateutil (==2.8.2)
Requires-Dist: pytz (==2022.1)
Requires-Dist: pyzmq (==23.2.0)
Requires-Dist: qtconsole (==5.3.1)
Requires-Dist: qtpy (==2.1.0)
Requires-Dist: requests (==2.28.1)
Requires-Dist: rsa (==4.9)
Requires-Dist: send2trash (==1.8.0)
Requires-Dist: six (==1.16.0)
Requires-Dist: soupsieve (==2.3.2.post1)
Requires-Dist: stack-data (==0.3.0)
Requires-Dist: terminado (==0.15.0)
Requires-Dist: testbook (==0.4.2)
Requires-Dist: testing-tools (==1.0.3)
Requires-Dist: tinycss2 (==1.1.1)
Requires-Dist: toml (==0.10.2)
Requires-Dist: tomli (==2.0.1)
Requires-Dist: tornado (==6.2)
Requires-Dist: tqdm (==4.64.0)
Requires-Dist: traitlets (==5.3.0)
Requires-Dist: typing-extensions (==4.3.0)
Requires-Dist: urllib3 (==1.26.11)
Requires-Dist: wcwidth (==0.2.5)
Requires-Dist: webencodings (==0.5.1)
Requires-Dist: wheel (==0.37.1)
Requires-Dist: widgetsnbextension (==3.6.1)
